.travis.yml
CHANGES.txt
CONTRIBUTORS.txt
README.md
development.ini
nonav.ini
setup.cfg
setup.py
todo.txt
tox.ini
docs/images/settings.png
kotti_navigation/__init__.py
kotti_navigation/fanstatic.py
kotti_navigation/populate.py
kotti_navigation/util.py
kotti_navigation/views.py
kotti_navigation.egg-info/PKG-INFO
kotti_navigation.egg-info/SOURCES.txt
kotti_navigation.egg-info/dependency_links.txt
kotti_navigation.egg-info/entry_points.txt
kotti_navigation.egg-info/not-zip-safe
kotti_navigation.egg-info/requires.txt
kotti_navigation.egg-info/top_level.txt
kotti_navigation/kotti-overrides/templates/view/nav.pt
kotti_navigation/locale/README
kotti_navigation/locale/kotti_navigation.pot
kotti_navigation/locale/de/LC_MESSAGES/kotti_navigation.po
kotti_navigation/locale/en/LC_MESSAGES/kotti_navigation.po
kotti_navigation/static/css/dropdown.css
kotti_navigation/static/css/dropdown.min.css
kotti_navigation/static/css/style.css
kotti_navigation/static/css/style.min.css
kotti_navigation/templates/nav_recurse.pt
kotti_navigation/templates/nav_recurse_dropdown.pt
kotti_navigation/templates/nav_widget_breadcrumbs.pt
kotti_navigation/templates/nav_widget_items.pt
kotti_navigation/templates/nav_widget_menu.pt
kotti_navigation/templates/nav_widget_top.pt
kotti_navigation/templates/nav_widget_tree.pt
kotti_navigation/tests/__init__.py
kotti_navigation/tests/conftest.py
kotti_navigation/tests/test_browser_breadcrumbs_top.rst
kotti_navigation/tests/test_browser_hor_tabs_top.rst
kotti_navigation/tests/test_browser_menu_top.rst
kotti_navigation/tests/test_browser_tree_top.rst
kotti_navigation/tests/test_browser_ver_list_top.rst
kotti_navigation/tests/test_navigation.py
kotti_navigation/tests/test_options.py