Metadata-Version: 1.1
Name: kotti-navigation
Version: 0.5
Summary: Add a configurable navigation to your Kotti site
Home-page: http://pypi.python.org/pypi/kotti_navigation
Author: Marco Scheidhuber
Author-email: j23d@jusid.de
License: BSD-derived (http://www.repoze.org/LICENSE.txt)
Keywords: kotti addon navigation
Platform: UNKNOWN
Classifier: Programming Language :: Python
Classifier: Programming Language :: Python :: 2.6
Classifier: Programming Language :: Python :: 2.7
Classifier: Framework :: Pylons
Classifier: Topic :: Internet :: WWW/HTTP
Classifier: Topic :: Internet :: WWW/HTTP :: Dynamic Content
Classifier: Topic :: Internet :: WWW/HTTP :: WSGI :: Application
Classifier: License :: Repoze Public License
